tools/.code_edit_roots.json
tools/.gitkeep
tools/__init__.py
tools/config.py
tools/edit.py
tools/filesystem.py
tools/mime_utils.py
tools/timeouts.py
main.py
server.py
code_editor_mcp-0.2.1.dist-info/METADATA
code_editor_mcp-0.2.1.dist-info/WHEEL
code_editor_mcp-0.2.1.dist-info/entry_points.txt
code_editor_mcp-0.2.1.dist-info/licenses/LICENSE
code_editor_mcp-0.2.1.dist-info/RECORD
