Metadata-Version: 2.4
Name: code-editor-mcp
Version: 0.2.1
Summary: Code editor MCP server with sandboxing, optimistic locking, and path whitelists.
Project-URL: Homepage, https://github.com/TripQi/code-editor
Project-URL: Repository, https://github.com/TripQi/code-editor
Project-URL: Issues, https://github.com/TripQi/code-editor/issues
Author: TripQi
License-Expression: MIT
License-File: LICENSE
Keywords: mcp,文件编辑
Classifier: Intended Audience :: Developers
Classifier: License :: OSI Approved :: MIT License
Classifier: Programming Language :: Python :: 3
Classifier: Programming Language :: Python :: 3 :: Only
Classifier: Programming Language :: Python :: 3.10
Classifier: Programming Language :: Python :: 3.11
Classifier: Programming Language :: Python :: 3.12
Classifier: Programming Language :: Python :: 3.13
Classifier: Topic :: Software Development :: Libraries
Requires-Python: >=3.10
Requires-Dist: charset-normalizer>=3.3.2
Requires-Dist: mcp>=1.22.0
